indico_payment_sixpay/__init__.py
indico_payment_sixpay/blueprint.py
indico_payment_sixpay/controllers.py
indico_payment_sixpay/forms.py
indico_payment_sixpay/plugin.py
indico_payment_sixpay/util.py
indico_payment_sixpay/templates/event_payment_form.html
indico_payment_sixpay/templates/transaction_details.html
indico_payment_sixpay/translations/messages.pot
indico_payment_sixpay/translations/cs_CZ/LC_MESSAGES/messages.mo
indico_payment_sixpay/translations/cs_CZ/LC_MESSAGES/messages.po
indico_payment_sixpay/translations/de_DE/LC_MESSAGES/messages.mo
indico_payment_sixpay/translations/de_DE/LC_MESSAGES/messages.po
indico_payment_sixpay/translations/en_CA/LC_MESSAGES/messages.mo
indico_payment_sixpay/translations/en_CA/LC_MESSAGES/messages.po
indico_payment_sixpay/translations/en_GB/LC_MESSAGES/messages.mo
indico_payment_sixpay/translations/en_GB/LC_MESSAGES/messages.po
indico_payment_sixpay/translations/es_ES/LC_MESSAGES/messages.mo
indico_payment_sixpay/translations/es_ES/LC_MESSAGES/messages.po
indico_payment_sixpay/translations/fr_FR/LC_MESSAGES/messages.mo
indico_payment_sixpay/translations/fr_FR/LC_MESSAGES/messages.po
indico_payment_sixpay/translations/hu_HU/LC_MESSAGES/messages.mo
indico_payment_sixpay/translations/hu_HU/LC_MESSAGES/messages.po
indico_payment_sixpay/translations/it_IT/LC_MESSAGES/messages.mo
indico_payment_sixpay/translations/it_IT/LC_MESSAGES/messages.po
indico_payment_sixpay/translations/ja_JP/LC_MESSAGES/messages.mo
indico_payment_sixpay/translations/ja_JP/LC_MESSAGES/messages.po
indico_payment_sixpay/translations/mn_MN/LC_MESSAGES/messages.mo
indico_payment_sixpay/translations/mn_MN/LC_MESSAGES/messages.po
indico_payment_sixpay/translations/pl_PL/LC_MESSAGES/messages.mo
indico_payment_sixpay/translations/pl_PL/LC_MESSAGES/messages.po
indico_payment_sixpay/translations/pt_BR/LC_MESSAGES/messages.mo
indico_payment_sixpay/translations/pt_BR/LC_MESSAGES/messages.po
indico_payment_sixpay/translations/sv_SE/LC_MESSAGES/messages.mo
indico_plugin_payment_sixpay-3.3.4.dist-info/METADATA
indico_plugin_payment_sixpay-3.3.4.dist-info/WHEEL
indico_plugin_payment_sixpay-3.3.4.dist-info/entry_points.txt
indico_plugin_payment_sixpay-3.3.4.dist-info/RECORD
