Metadata-Version: 2.4
Name: indico-plugin-payment-sixpay
Version: 3.3.4
Summary: SIXPay/Saferpay payments for Indico event registration fees
Project-URL: GitHub, https://github.com/indico/indico-plugins
Author-email: Indico Team <indico-team@cern.ch>, Max Fischer <maxfischer2781@gmail.com>, Martin Claus <mclaus@geomar.de>
License-Expression: MIT
Classifier: Environment :: Plugins
Classifier: Environment :: Web Environment
Classifier: License :: OSI Approved :: MIT License
Classifier: Programming Language :: Python :: 3.12
Requires-Python: <3.13,>=3.12.2
Requires-Dist: indico>=3.3
Requires-Dist: iso4217==1.12.20240625
